minimulti/__init__.py
minimulti/constants.py
minimulti/LWF/__init__.py
minimulti/LWF/lwf.py
minimulti/LWF/lwf_to_atoms_batch.py
minimulti/abstract/__init__.py
minimulti/abstract/abstract_coupling.py
minimulti/abstract/abstract_hamiltonian.py
minimulti/abstract/abstract_model.py
minimulti/abstract/abstract_mover.py
minimulti/abstract/abstract_potential.py
minimulti/abstract/datatype.py
minimulti/electron/COHP.py
minimulti/electron/HF.py
minimulti/electron/Hamiltonian.py
minimulti/electron/Hubbard.py
minimulti/electron/Hubbard_4ind.py
minimulti/electron/UJfitter.py
minimulti/electron/U_matrix.py
minimulti/electron/__init__.py
minimulti/electron/basis2.py
minimulti/electron/constraint.py
minimulti/electron/density.py
minimulti/electron/epc.py
minimulti/electron/from_banddownfolder.py
minimulti/electron/hopping.py
minimulti/electron/ijR.py
minimulti/electron/ioput.py
minimulti/electron/lwf.py
minimulti/electron/mixing.py
minimulti/electron/modifier.py
minimulti/electron/myNN.py
minimulti/electron/mytb.py
minimulti/electron/occupations.py
minimulti/electron/pdos.py
minimulti/electron/plot.py
minimulti/electron/pythtb.py
minimulti/electron/spherical_harmonic.py
minimulti/electron/supercell.py
minimulti/electron/susceptibility.py
minimulti/electron/test_pert.py
minimulti/electron/utils.py
minimulti/electron/wannier90.py
minimulti/electron/TB/__init__.py
minimulti/electron/TB/myTB.py
minimulti/electron/TB/mypythtb.py
minimulti/electron/box/__init__.py
minimulti/electron/box/dummymixer.py
minimulti/electron/box/pulay.py
minimulti/electron/builder/__init__.py
minimulti/electron/builder/perovskite.py
minimulti/ioput/__init__.py
minimulti/ioput/base_parser.py
minimulti/ioput/ifc_netcdf.py
minimulti/ioput/ifc_parser.py
minimulti/ioput/spin_nc.py
minimulti/ioput/spin_pot_nc.py
minimulti/ioput/spin_ucl.py
minimulti/ioput/spin_xml.py
minimulti/ioput/to_hdf.py
minimulti/lattice/__init__.py
minimulti/lattice/file_io.py
minimulti/lattice/latt_obs.py
minimulti/lattice/lattice.py
minimulti-0.3.14.dist-info/LICENSE
minimulti-0.3.14.dist-info/METADATA
minimulti-0.3.14.dist-info/WHEEL
minimulti-0.3.14.dist-info/top_level.txt
minimulti-0.3.14.dist-info/RECORD
