Metadata-Version: 2.1
Name: minimulti
Version: 0.3.14
Summary: Mini Extendable framework of multi Hamiltonian
Home-page: UNKNOWN
Author: Xu He
Author-email: mailhexu@gmail.com
License: GPLv3
Platform: UNKNOWN
Classifier: Development Status :: 3 - Alpha
License-File: LICENSE
Requires-Dist: ase
Requires-Dist: jupyter
Requires-Dist: matplotlib
Requires-Dist: netcdf4
Requires-Dist: numba
Requires-Dist: numpy
Requires-Dist: scipy
Requires-Dist: tbmodels
